Metadata-Version: 2.4
Name: pokemon-gba-env
Version: 0.1.0
Summary: A wrapper with emulation, state parsing and low-level control modules for Pokemon Red
Requires-Python: >=3.12.2
License-File: LICENSE
Requires-Dist: click>=8.3.0
Requires-Dist: matplotlib>=3.10.7
Requires-Dist: mediapy>=1.2.4
Requires-Dist: numpy>=2.3.4
Requires-Dist: pyboy==2.4.0
Requires-Dist: pyyaml>=6.0.3
Requires-Dist: scikit-image>=0.25.2
Dynamic: license-file
